chatbot_core/__init__.py
chatbot_core/chatbot_abc.py
chatbot_core/cli.py
chatbot_core/neon.py
chatbot_core/parlai.py
chatbot_core/version.py
chatbot_core/utils/__init__.py
chatbot_core/utils/bot_utils.py
chatbot_core/utils/cache.py
chatbot_core/utils/conversation_utils.py
chatbot_core/utils/enum.py
chatbot_core/utils/logger.py
chatbot_core/utils/string_utils.py
chatbot_core/utils/version_utils.py
chatbot_core/v1/__init__.py
chatbot_core/v2/__init__.py
tests/__init__.py
tests/chatbot_objects.py
tests/integration/__init__.py
tests/integration/v1/__init__.py
tests/integration/v1/test_chatbot_core.py
tests/integration/v2/__init__.py
tests/integration/v2/mocks.py
tests/integration/v2/test_proctored_conversation.py
tests/units/__init__.py
tests/units/mocks.py
tests/units/test_base_classes.py
tests/units/test_init.py
tests/units/test_utils.py
neon_chatbot_core-2.4.1a5.dist-info/LICENSE.md
neon_chatbot_core-2.4.1a5.dist-info/METADATA
neon_chatbot_core-2.4.1a5.dist-info/WHEEL
neon_chatbot_core-2.4.1a5.dist-info/entry_points.txt
neon_chatbot_core-2.4.1a5.dist-info/top_level.txt
neon_chatbot_core-2.4.1a5.dist-info/RECORD
