Metadata-Version: 2.1
Name: neon-chatbot-core
Version: 2.4.1a5
Summary: Core utilities for Klat chatbots
Home-page: https://github.com/neongeckocom/chatbot-core
Author: Neongecko
Author-email: developers@neon.ai
Classifier: Programming Language :: Python :: 3
Classifier: Operating System :: OS Independent
Requires-Python: >=3.6
License-File: LICENSE.md
Requires-Dist: click~=8.0
Requires-Dist: klat-connector~=0.8
Requires-Dist: neon-mq-connector>=0.9.1a1,~=0.8
Requires-Dist: neon-utils[network,sentry]~=1.13
Requires-Dist: ovos-utils~=0.0
Requires-Dist: ovos-bus-client>=0.0.5,~=0.0
Requires-Dist: psutil~=5.7
Requires-Dist: neon-data-models>=0.0.2a12,~=0.0
Provides-Extra: lang
Requires-Dist: jellyfish~=0.8; extra == "lang"
Requires-Dist: nltk~=3.5; extra == "lang"
Requires-Dist: spacy~=2.3.1; extra == "lang"
Provides-Extra: lgpl
Requires-Dist: autocorrect~=2.2.2; extra == "lgpl"
